odapdbxbundle/common/databricks.py
odapdbxbundle/common/logger.py
odapdbxbundle/keboola.py
odapdbxbundle/optimize.py
odapdbxbundle/secrets.py
odapdbxbundle-0.1.0.dist-info/LICENSE
odapdbxbundle-0.1.0.dist-info/WHEEL
odapdbxbundle-0.1.0.dist-info/METADATA
odapdbxbundle-0.1.0.dist-info/RECORD
