Metadata-Version: 2.1
Name: odapdbxbundle
Version: 0.1.0
Summary: ODAP Databricks Bundle
License: Proprietary
Author: Tomas Bouma
Author-email: tomas.bouma@datasentics.com
Requires-Python: >=3.8,<4.0
Classifier: License :: Other/Proprietary License
Classifier: Programming Language :: Python :: 3
Classifier: Programming Language :: Python :: 3.8
Classifier: Programming Language :: Python :: 3.9
Requires-Dist: databricks_api
Requires-Dist: kbcstorage (>=0.0.1,<0.0.2)
Requires-Dist: pyyaml (>=6.0,<7.0)
